README
setup.py
pyramid_mountable/__init__.py
pyramid_mountable/_impl.py
pyramid_mountable.egg-info/PKG-INFO
pyramid_mountable.egg-info/SOURCES.txt
pyramid_mountable.egg-info/dependency_links.txt
pyramid_mountable.egg-info/requires.txt
pyramid_mountable.egg-info/top_level.txt