Metadata-Version: 1.1
Name: pyramid-mountable
Version: 0.1
Summary: Provide a mountable tree to the ease creation of traversal root for pyramid
Home-page: UNKNOWN
Author: Sherwood Wang
Author-email: sherwood@wang.onl
License: UNKNOWN
Platform: UNKNOWN
Classifier: Programming Language :: Python
Classifier: Framework :: Pyramid
Classifier: Topic :: Internet :: WWW/HTTP
